[
  {
    "name": "Beauvechain",
    "slug": "beauvechain-1320",
    "zip": "1320",
    "province_name": "Brabant wallon",
    "province_code": "BW",
    "region": "Wallonie",
    "coordinates": {
      "lat": 50.7833,
      "lng": 4.7667
    },
    "population": 7200
  },
  {
    "name": "Braine-l'Alleud",
    "slug": "braine-lalleud-1420",
    "zip": "1420",
    "province_name": "Brabant wallon",
    "province_code": "BW",
    "region": "Wallonie",
    "coordinates": {
      "lat": 50.6833,
      "lng": 4.3667
    },
    "population": 40394
  },
  {
    "name": "Braine-le-Château",
    "slug": "braine-le-chateau-1440",
    "zip": "1440",
    "province_name": "Brabant wallon",
    "province_code": "BW",
    "region": "Wallonie",
    "coordinates": {
      "lat": 50.6833,
      "lng": 4.2667
    },
    "population": 10742
  },
  {
    "name": "Chastre",
    "slug": "chastre-1450",
    "zip": "1450",
    "province_name": "Brabant wallon",
    "province_code": "BW",
    "region": "Wallonie",
    "coordinates": {
      "lat": 50.5833,
      "lng": 4.6333
    },
    "population": 7825
  },
  {
    "name": "Chaumont-Gistoux",
    "slug": "chaumont-gistoux-1325",
    "zip": "1325",
    "province_name": "Brabant wallon",
    "province_code": "BW",
    "region": "Wallonie",
    "coordinates": {
      "lat": 50.7167,
      "lng": 4.7
    },
    "population": 11800
  },
  {
    "name": "Court-Saint-Étienne",
    "slug": "court-saint-etienne-1490",
    "zip": "1490",
    "province_name": "Brabant wallon",
    "province_code": "BW",
    "region": "Wallonie",
    "coordinates": {
      "lat": 50.6333,
      "lng": 4.5667
    },
    "population": 10582
  },
  {
    "name": "Genappe",
    "slug": "genappe-1470",
    "zip": "1470",
    "province_name": "Brabant wallon",
    "province_code": "BW",
    "region": "Wallonie",
    "coordinates": {
      "lat": 50.6167,
      "lng": 4.45
    },
    "population": 16107
  },
  {
    "name": "Hélécine",
    "slug": "helecine-1357",
    "zip": "1357",
    "province_name": "Brabant wallon",
    "province_code": "BW",
    "region": "Wallonie",
    "coordinates": {
      "lat": 50.7333,
      "lng": 5.0833
    },
    "population": 3500
  },
  {
    "name": "Incourt",
    "slug": "incourt-1315",
    "zip": "1315",
    "province_name": "Brabant wallon",
    "province_code": "BW",
    "region": "Wallonie",
    "coordinates": {
      "lat": 50.6833,
      "lng": 4.8
    },
    "population": 5200
  },
  {
    "name": "Ittre",
    "slug": "ittre-1460",
    "zip": "1460",
    "province_name": "Brabant wallon",
    "province_code": "BW",
    "region": "Wallonie",
    "coordinates": {
      "lat": 50.6333,
      "lng": 4.2667
    },
    "population": 7233
  },
  {
    "name": "Jodoigne",
    "slug": "jodoigne-1370",
    "zip": "1370",
    "province_name": "Brabant wallon",
    "province_code": "BW",
    "region": "Wallonie",
    "coordinates": {
      "lat": 50.725,
      "lng": 4.8667
    },
    "population": 14424
  },
  {
    "name": "La Hulpe",
    "slug": "la-hulpe-1310",
    "zip": "1310",
    "province_name": "Brabant wallon",
    "province_code": "BW",
    "region": "Wallonie",
    "coordinates": {
      "lat": 50.7333,
      "lng": 4.4833
    },
    "population": 7500
  },
  {
    "name": "Lasne",
    "slug": "lasne-1380",
    "zip": "1380",
    "province_name": "Brabant wallon",
    "province_code": "BW",
    "region": "Wallonie",
    "coordinates": {
      "lat": 50.6833,
      "lng": 4.5
    },
    "population": 14200
  },
  {
    "name": "Mont-Saint-Guibert",
    "slug": "mont-saint-guibert-1435",
    "zip": "1435",
    "province_name": "Brabant wallon",
    "province_code": "BW",
    "region": "Wallonie",
    "coordinates": {
      "lat": 50.6333,
      "lng": 4.6167
    },
    "population": 7564
  },
  {
    "name": "Nivelles",
    "slug": "nivelles-1400",
    "zip": "1400",
    "province_name": "Brabant wallon",
    "province_code": "BW",
    "region": "Wallonie",
    "coordinates": {
      "lat": 50.5989,
      "lng": 4.3292
    },
    "population": 28929
  },
  {
    "name": "Orp-Jauche",
    "slug": "orp-jauche-1350",
    "zip": "1350",
    "province_name": "Brabant wallon",
    "province_code": "BW",
    "region": "Wallonie",
    "coordinates": {
      "lat": 50.7167,
      "lng": 4.9833
    },
    "population": 8800
  },
  {
    "name": "Ottignies-Louvain-la-Neuve",
    "slug": "ottignies-louvain-la-neuve-1340",
    "zip": "1340",
    "province_name": "Brabant wallon",
    "province_code": "BW",
    "region": "Wallonie",
    "coordinates": {
      "lat": 50.6667,
      "lng": 4.5667
    },
    "population": 32399
  },
  {
    "name": "Perwez",
    "slug": "perwez-1360",
    "zip": "1360",
    "province_name": "Brabant wallon",
    "province_code": "BW",
    "region": "Wallonie",
    "coordinates": {
      "lat": 50.6333,
      "lng": 4.8167
    },
    "population": 9452
  },
  {
    "name": "Ramillies",
    "slug": "ramillies-1367",
    "zip": "1367",
    "province_name": "Brabant wallon",
    "province_code": "BW",
    "region": "Wallonie",
    "coordinates": {
      "lat": 50.6333,
      "lng": 4.9
    },
    "population": 6300
  },
  {
    "name": "Rebecq",
    "slug": "rebecq-1430",
    "zip": "1430",
    "province_name": "Brabant wallon",
    "province_code": "BW",
    "region": "Wallonie",
    "coordinates": {
      "lat": 50.6667,
      "lng": 4.1333
    },
    "population": 10914
  },
  {
    "name": "Rixensart",
    "slug": "rixensart-1330",
    "zip": "1330",
    "province_name": "Brabant wallon",
    "province_code": "BW",
    "region": "Wallonie",
    "coordinates": {
      "lat": 50.7167,
      "lng": 4.5333
    },
    "population": 22645
  },
  {
    "name": "Tubize",
    "slug": "tubize-1480",
    "zip": "1480",
    "province_name": "Brabant wallon",
    "province_code": "BW",
    "region": "Wallonie",
    "coordinates": {
      "lat": 50.6917,
      "lng": 4.2
    },
    "population": 26199
  },
  {
    "name": "Villers-la-Ville",
    "slug": "villers-la-ville-1495",
    "zip": "1495",
    "province_name": "Brabant wallon",
    "province_code": "BW",
    "region": "Wallonie",
    "coordinates": {
      "lat": 50.5833,
      "lng": 4.5333
    },
    "population": 10697
  },
  {
    "name": "Walhain",
    "slug": "walhain-1457",
    "zip": "1457",
    "province_name": "Brabant wallon",
    "province_code": "BW",
    "region": "Wallonie",
    "coordinates": {
      "lat": 50.6167,
      "lng": 4.6833
    },
    "population": 7267
  },
  {
    "name": "Waterloo",
    "slug": "waterloo-1410",
    "zip": "1410",
    "province_name": "Brabant wallon",
    "province_code": "BW",
    "region": "Wallonie",
    "coordinates": {
      "lat": 50.7167,
      "lng": 4.4
    },
    "population": 30382
  },
  {
    "name": "Wavre",
    "slug": "wavre-1300",
    "zip": "1300",
    "province_name": "Brabant wallon",
    "province_code": "BW",
    "region": "Wallonie",
    "coordinates": {
      "lat": 50.7167,
      "lng": 4.6
    },
    "population": 34487
  },
  {
    "name": "Anderlecht",
    "slug": "anderlecht-1070",
    "zip": "1070",
    "province_name": "Bruxelles-Capitale",
    "province_code": "BXL",
    "region": "Bruxelles-Capitale",
    "coordinates": {
      "lat": 50.8366,
      "lng": 4.307
    },
    "population": 120526
  },
  {
    "name": "Auderghem",
    "slug": "auderghem-1160",
    "zip": "1160",
    "province_name": "Bruxelles-Capitale",
    "province_code": "BXL",
    "region": "Bruxelles-Capitale",
    "coordinates": {
      "lat": 50.8167,
      "lng": 4.4333
    },
    "population": 34032
  },
  {
    "name": "Berchem-Sainte-Agathe",
    "slug": "berchem-sainte-agathe-1082",
    "zip": "1082",
    "province_name": "Bruxelles-Capitale",
    "province_code": "BXL",
    "region": "Bruxelles-Capitale",
    "coordinates": {
      "lat": 50.8667,
      "lng": 4.2917
    },
    "population": 25175
  },
  {
    "name": "Bruxelles",
    "slug": "bruxelles-1000",
    "zip": "1000",
    "province_name": "Bruxelles-Capitale",
    "province_code": "BXL",
    "region": "Bruxelles-Capitale",
    "coordinates": {
      "lat": 50.8503,
      "lng": 4.3517
    },
    "population": 185103
  },
  {
    "name": "Etterbeek",
    "slug": "etterbeek-1040",
    "zip": "1040",
    "province_name": "Bruxelles-Capitale",
    "province_code": "BXL",
    "region": "Bruxelles-Capitale",
    "coordinates": {
      "lat": 50.8381,
      "lng": 4.3886
    },
    "population": 48365
  },
  {
    "name": "Evere",
    "slug": "evere-1140",
    "zip": "1140",
    "province_name": "Bruxelles-Capitale",
    "province_code": "BXL",
    "region": "Bruxelles-Capitale",
    "coordinates": {
      "lat": 50.8667,
      "lng": 4.4
    },
    "population": 42693
  },
  {
    "name": "Forest",
    "slug": "forest-1190",
    "zip": "1190",
    "province_name": "Bruxelles-Capitale",
    "province_code": "BXL",
    "region": "Bruxelles-Capitale",
    "coordinates": {
      "lat": 50.81,
      "lng": 4.32
    },
    "population": 56289
  },
  {
    "name": "Ganshoren",
    "slug": "ganshoren-1083",
    "zip": "1083",
    "province_name": "Bruxelles-Capitale",
    "province_code": "BXL",
    "region": "Bruxelles-Capitale",
    "coordinates": {
      "lat": 50.875,
      "lng": 4.3083
    },
    "population": 24885
  },
  {
    "name": "Ixelles",
    "slug": "ixelles-1050",
    "zip": "1050",
    "province_name": "Bruxelles-Capitale",
    "province_code": "BXL",
    "region": "Bruxelles-Capitale",
    "coordinates": {
      "lat": 50.8275,
      "lng": 4.3719
    },
    "population": 87517
  },
  {
    "name": "Jette",
    "slug": "jette-1090",
    "zip": "1090",
    "province_name": "Bruxelles-Capitale",
    "province_code": "BXL",
    "region": "Bruxelles-Capitale",
    "coordinates": {
      "lat": 50.8783,
      "lng": 4.3244
    },
    "population": 52536
  },
  {
    "name": "Koekelberg",
    "slug": "koekelberg-1081",
    "zip": "1081",
    "province_name": "Bruxelles-Capitale",
    "province_code": "BXL",
    "region": "Bruxelles-Capitale",
    "coordinates": {
      "lat": 50.8633,
      "lng": 4.3317
    },
    "population": 22121
  },
  {
    "name": "Molenbeek-Saint-Jean",
    "slug": "molenbeek-saint-jean-1080",
    "zip": "1080",
    "province_name": "Bruxelles-Capitale",
    "province_code": "BXL",
    "region": "Bruxelles-Capitale",
    "coordinates": {
      "lat": 50.856,
      "lng": 4.325
    },
    "population": 97462
  },
  {
    "name": "Saint-Gilles",
    "slug": "saint-gilles-1060",
    "zip": "1060",
    "province_name": "Bruxelles-Capitale",
    "province_code": "BXL",
    "region": "Bruxelles-Capitale",
    "coordinates": {
      "lat": 50.8267,
      "lng": 4.3467
    },
    "population": 50471
  },
  {
    "name": "Saint-Josse-ten-Noode",
    "slug": "saint-josse-ten-noode-1210",
    "zip": "1210",
    "province_name": "Bruxelles-Capitale",
    "province_code": "BXL",
    "region": "Bruxelles-Capitale",
    "coordinates": {
      "lat": 50.855,
      "lng": 4.3717
    },
    "population": 27747
  },
  {
    "name": "Schaerbeek",
    "slug": "schaerbeek-1030",
    "zip": "1030",
    "province_name": "Bruxelles-Capitale",
    "province_code": "BXL",
    "region": "Bruxelles-Capitale",
    "coordinates": {
      "lat": 50.8676,
      "lng": 4.3792
    },
    "population": 133042
  },
  {
    "name": "Uccle",
    "slug": "uccle-1180",
    "zip": "1180",
    "province_name": "Bruxelles-Capitale",
    "province_code": "BXL",
    "region": "Bruxelles-Capitale",
    "coordinates": {
      "lat": 50.8,
      "lng": 4.3333
    },
    "population": 83024
  },
  {
    "name": "Watermael-Boitsfort",
    "slug": "watermael-boitsfort-1170",
    "zip": "1170",
    "province_name": "Bruxelles-Capitale",
    "province_code": "BXL",
    "region": "Bruxelles-Capitale",
    "coordinates": {
      "lat": 50.8,
      "lng": 4.4
    },
    "population": 25326
  },
  {
    "name": "Woluwe-Saint-Lambert",
    "slug": "woluwe-saint-lambert-1200",
    "zip": "1200",
    "province_name": "Bruxelles-Capitale",
    "province_code": "BXL",
    "region": "Bruxelles-Capitale",
    "coordinates": {
      "lat": 50.85,
      "lng": 4.4333
    },
    "population": 56090
  },
  {
    "name": "Woluwe-Saint-Pierre",
    "slug": "woluwe-saint-pierre-1150",
    "zip": "1150",
    "province_name": "Bruxelles-Capitale",
    "province_code": "BXL",
    "region": "Bruxelles-Capitale",
    "coordinates": {
      "lat": 50.8333,
      "lng": 4.4167
    },
    "population": 41882
  },
  {
    "name": "Aiseau-Presles",
    "slug": "aiseau-presles-6250",
    "zip": "6250",
    "province_name": "Hainaut",
    "province_code": "HT",
    "region": "Wallonie",
    "coordinates": {
      "lat": 50.4,
      "lng": 4.5833
    },
    "population": 10963
  },
  {
    "name": "Anderlues",
    "slug": "anderlues-6150",
    "zip": "6150",
    "province_name": "Hainaut",
    "province_code": "HT",
    "region": "Wallonie",
    "coordinates": {
      "lat": 50.4,
      "lng": 4.2667
    },
    "population": 12195
  },
  {
    "name": "Antoing",
    "slug": "antoing-7640",
    "zip": "7640",
    "province_name": "Hainaut",
    "province_code": "HT",
    "region": "Wallonie",
    "coordinates": {
      "lat": 50.5667,
      "lng": 3.45
    },
    "population": 7864
  },
  {
    "name": "Ath",
    "slug": "ath-7800",
    "zip": "7800",
    "province_name": "Hainaut",
    "province_code": "HT",
    "region": "Wallonie",
    "coordinates": {
      "lat": 50.6294,
      "lng": 3.7781
    },
    "population": 29655
  },
  {
    "name": "Beaumont",
    "slug": "beaumont-6500",
    "zip": "6500",
    "province_name": "Hainaut",
    "province_code": "HT",
    "region": "Wallonie",
    "coordinates": {
      "lat": 50.2333,
      "lng": 4.2333
    },
    "population": 7294
  },
  {
    "name": "Beloeil",
    "slug": "beloeil-7970",
    "zip": "7970",
    "province_name": "Hainaut",
    "province_code": "HT",
    "region": "Wallonie",
    "coordinates": {
      "lat": 50.55,
      "lng": 3.7333
    },
    "population": 14025
  },
  {
    "name": "Bernissart",
    "slug": "bernissart-7320",
    "zip": "7320",
    "province_name": "Hainaut",
    "province_code": "HT",
    "region": "Wallonie",
    "coordinates": {
      "lat": 50.4833,
      "lng": 3.65
    },
    "population": 11779
  },
  {
    "name": "Binche",
    "slug": "binche-7130",
    "zip": "7130",
    "province_name": "Hainaut",
    "province_code": "HT",
    "region": "Wallonie",
    "coordinates": {
      "lat": 50.4114,
      "lng": 4.1647
    },
    "population": 33431
  },
  {
    "name": "Boussu",
    "slug": "boussu-7300",
    "zip": "7300",
    "province_name": "Hainaut",
    "province_code": "HT",
    "region": "Wallonie",
    "coordinates": {
      "lat": 50.4333,
      "lng": 3.8
    },
    "population": 20216
  },
  {
    "name": "Braine-le-Comte",
    "slug": "braine-le-comte-7090",
    "zip": "7090",
    "province_name": "Hainaut",
    "province_code": "HT",
    "region": "Wallonie",
    "coordinates": {
      "lat": 50.61,
      "lng": 4.1317
    },
    "population": 22285
  },
  {
    "name": "Brugelette",
    "slug": "brugelette-7940",
    "zip": "7940",
    "province_name": "Hainaut",
    "province_code": "HT",
    "region": "Wallonie",
    "coordinates": {
      "lat": 50.5833,
      "lng": 3.85
    },
    "population": 3600
  },
  {
    "name": "Brunehaut",
    "slug": "brunehaut-7620",
    "zip": "7620",
    "province_name": "Hainaut",
    "province_code": "HT",
    "region": "Wallonie",
    "coordinates": {
      "lat": 50.5,
      "lng": 3.4
    },
    "population": 8100
  },
  {
    "name": "Celles",
    "slug": "celles-7760",
    "zip": "7760",
    "province_name": "Hainaut",
    "province_code": "HT",
    "region": "Wallonie",
    "coordinates": {
      "lat": 50.7,
      "lng": 3.45
    },
    "population": 5678
  },
  {
    "name": "Cerfontaine",
    "slug": "cerfontaine-5630",
    "zip": "5630",
    "province_name": "Hainaut",
    "province_code": "HT",
    "region": "Wallonie",
    "coordinates": {
      "lat": 50.1667,
      "lng": 4.3833
    },
    "population": 4900
  },
  {
    "name": "Chapelle-lez-Herlaimont",
    "slug": "chapelle-lez-herlaimont-7160",
    "zip": "7160",
    "province_name": "Hainaut",
    "province_code": "HT",
    "region": "Wallonie",
    "coordinates": {
      "lat": 50.4667,
      "lng": 4.2833
    },
    "population": 14845
  },
  {
    "name": "Charleroi",
    "slug": "charleroi-6000",
    "zip": "6000",
    "province_name": "Hainaut",
    "province_code": "HT",
    "region": "Wallonie",
    "coordinates": {
      "lat": 50.4108,
      "lng": 4.4446
    },
    "population": 202480
  },
  {
    "name": "Chimay",
    "slug": "chimay-6460",
    "zip": "6460",
    "province_name": "Hainaut",
    "province_code": "HT",
    "region": "Wallonie",
    "coordinates": {
      "lat": 50.05,
      "lng": 4.3167
    },
    "population": 9979
  },
  {
    "name": "Chièvres",
    "slug": "chievres-7950",
    "zip": "7950",
    "province_name": "Hainaut",
    "province_code": "HT",
    "region": "Wallonie",
    "coordinates": {
      "lat": 50.5833,
      "lng": 3.8
    },
    "population": 6976
  },
  {
    "name": "Châtelet",
    "slug": "chatelet-6200",
    "zip": "6200",
    "province_name": "Hainaut",
    "province_code": "HT",
    "region": "Wallonie",
    "coordinates": {
      "lat": 50.4,
      "lng": 4.5333
    },
    "population": 36131
  },
  {
    "name": "Colfontaine",
    "slug": "colfontaine-7340",
    "zip": "7340",
    "province_name": "Hainaut",
    "province_code": "HT",
    "region": "Wallonie",
    "coordinates": {
      "lat": 50.4,
      "lng": 3.85
    },
    "population": 20680
  },
  {
    "name": "Comines-Warneton",
    "slug": "comines-warneton-7780",
    "zip": "7780",
    "province_name": "Hainaut",
    "province_code": "HT",
    "region": "Wallonie",
    "coordinates": {
      "lat": 50.7667,
      "lng": 3.0
    },
    "population": 18160
  },
  {
    "name": "Courcelles",
    "slug": "courcelles-6180",
    "zip": "6180",
    "province_name": "Hainaut",
    "province_code": "HT",
    "region": "Wallonie",
    "coordinates": {
      "lat": 50.4633,
      "lng": 4.3717
    },
    "population": 31272
  },
  {
    "name": "Dour",
    "slug": "dour-7370",
    "zip": "7370",
    "province_name": "Hainaut",
    "province_code": "HT",
    "region": "Wallonie",
    "coordinates": {
      "lat": 50.3967,
      "lng": 3.7775
    },
    "population": 17241
  },
  {
    "name": "Ecaussinnes",
    "slug": "ecaussinnes-7190",
    "zip": "7190",
    "province_name": "Hainaut",
    "province_code": "HT",
    "region": "Wallonie",
    "coordinates": {
      "lat": 50.5667,
      "lng": 4.1667
    },
    "population": 11305
  },
  {
    "name": "Ellezelles",
    "slug": "ellezelles-7890",
    "zip": "7890",
    "province_name": "Hainaut",
    "province_code": "HT",
    "region": "Wallonie",
    "coordinates": {
      "lat": 50.7333,
      "lng": 3.6833
    },
    "population": 5900
  },
  {
    "name": "Enghien",
    "slug": "enghien-7850",
    "zip": "7850",
    "province_name": "Hainaut",
    "province_code": "HT",
    "region": "Wallonie",
    "coordinates": {
      "lat": 50.6911,
      "lng": 4.0375
    },
    "population": 14005
  },
  {
    "name": "Erquelinnes",
    "slug": "erquelinnes-6560",
    "zip": "6560",
    "province_name": "Hainaut",
    "province_code": "HT",
    "region": "Wallonie",
    "coordinates": {
      "lat": 50.3,
      "lng": 4.1167
    },
    "population": 10037
  },
  {
    "name": "Estaimpuis",
    "slug": "estaimpuis-7730",
    "zip": "7730",
    "province_name": "Hainaut",
    "province_code": "HT",
    "region": "Wallonie",
    "coordinates": {
      "lat": 50.7,
      "lng": 3.2667
    },
    "population": 10308
  },
  {
    "name": "Estinnes",
    "slug": "estinnes-7120",
    "zip": "7120",
    "province_name": "Hainaut",
    "province_code": "HT",
    "region": "Wallonie",
    "coordinates": {
      "lat": 50.3833,
      "lng": 4.1
    },
    "population": 7906
  },
  {
    "name": "Farciennes",
    "slug": "farciennes-6240",
    "zip": "6240",
    "province_name": "Hainaut",
    "province_code": "HT",
    "region": "Wallonie",
    "coordinates": {
      "lat": 50.4333,
      "lng": 4.55
    },
    "population": 11613
  },
  {
    "name": "Fleurus",
    "slug": "fleurus-6220",
    "zip": "6220",
    "province_name": "Hainaut",
    "province_code": "HT",
    "region": "Wallonie",
    "coordinates": {
      "lat": 50.4833,
      "lng": 4.55
    },
    "population": 23047
  },
  {
    "name": "Flobecq",
    "slug": "flobecq-7880",
    "zip": "7880",
    "province_name": "Hainaut",
    "province_code": "HT",
    "region": "Wallonie",
    "coordinates": {
      "lat": 50.75,
      "lng": 3.7333
    },
    "population": 3600
  },
  {
    "name": "Fontaine-l'Évêque",
    "slug": "fontaine-leveque-6140",
    "zip": "6140",
    "province_name": "Hainaut",
    "province_code": "HT",
    "region": "Wallonie",
    "coordinates": {
      "lat": 50.3989,
      "lng": 4.3283
    },
    "population": 17685
  },
  {
    "name": "Frameries",
    "slug": "frameries-7080",
    "zip": "7080",
    "province_name": "Hainaut",
    "province_code": "HT",
    "region": "Wallonie",
    "coordinates": {
      "lat": 50.4078,
      "lng": 3.8964
    },
    "population": 21956
  },
  {
    "name": "Frasnes-lez-Anvaing",
    "slug": "frasnes-lez-anvaing-7910",
    "zip": "7910",
    "province_name": "Hainaut",
    "province_code": "HT",
    "region": "Wallonie",
    "coordinates": {
      "lat": 50.6667,
      "lng": 3.5833
    },
    "population": 11500
  },
  {
    "name": "Froidchapelle",
    "slug": "froidchapelle-6440",
    "zip": "6440",
    "province_name": "Hainaut",
    "province_code": "HT",
    "region": "Wallonie",
    "coordinates": {
      "lat": 50.15,
      "lng": 4.3333
    },
    "population": 3800
  },
  {
    "name": "Gerpinnes",
    "slug": "gerpinnes-6280",
    "zip": "6280",
    "province_name": "Hainaut",
    "province_code": "HT",
    "region": "Wallonie",
    "coordinates": {
      "lat": 50.3333,
      "lng": 4.5167
    },
    "population": 12709
  },
  {
    "name": "Ham-sur-Heure-Nalinnes",
    "slug": "ham-sur-heure-nalinnes-6120",
    "zip": "6120",
    "province_name": "Hainaut",
    "province_code": "HT",
    "region": "Wallonie",
    "coordinates": {
      "lat": 50.3167,
      "lng": 4.3833
    },
    "population": 14178
  },
  {
    "name": "Hensies",
    "slug": "hensies-7350",
    "zip": "7350",
    "province_name": "Hainaut",
    "province_code": "HT",
    "region": "Wallonie",
    "coordinates": {
      "lat": 50.4333,
      "lng": 3.6833
    },
    "population": 6900
  },
  {
    "name": "Honnelles",
    "slug": "honnelles-7387",
    "zip": "7387",
    "province_name": "Hainaut",
    "province_code": "HT",
    "region": "Wallonie",
    "coordinates": {
      "lat": 50.35,
      "lng": 3.7167
    },
    "population": 5200
  },
  {
    "name": "Jurbise",
    "slug": "jurbise-7050",
    "zip": "7050",
    "province_name": "Hainaut",
    "province_code": "HT",
    "region": "Wallonie",
    "coordinates": {
      "lat": 50.5333,
      "lng": 3.9167
    },
    "population": 10459
  },
  {
    "name": "La Louvière",
    "slug": "la-louviere-7100",
    "zip": "7100",
    "province_name": "Hainaut",
    "province_code": "HT",
    "region": "Wallonie",
    "coordinates": {
      "lat": 50.4714,
      "lng": 4.1858
    },
    "population": 80986
  },
  {
    "name": "Le Roeulx",
    "slug": "le-roeulx-7070",
    "zip": "7070",
    "province_name": "Hainaut",
    "province_code": "HT",
    "region": "Wallonie",
    "coordinates": {
      "lat": 50.5,
      "lng": 4.1167
    },
    "population": 8555
  },
  {
    "name": "Lens",
    "slug": "lens-7870",
    "zip": "7870",
    "province_name": "Hainaut",
    "province_code": "HT",
    "region": "Wallonie",
    "coordinates": {
      "lat": 50.55,
      "lng": 3.85
    },
    "population": 4400
  },
  {
    "name": "Lessines",
    "slug": "lessines-7860",
    "zip": "7860",
    "province_name": "Hainaut",
    "province_code": "HT",
    "region": "Wallonie",
    "coordinates": {
      "lat": 50.7117,
      "lng": 3.8333
    },
    "population": 18692
  },
  {
    "name": "Leuze-en-Hainaut",
    "slug": "leuze-en-hainaut-7900",
    "zip": "7900",
    "province_name": "Hainaut",
    "province_code": "HT",
    "region": "Wallonie",
    "coordinates": {
      "lat": 50.6,
      "lng": 3.6167
    },
    "population": 13812
  },
  {
    "name": "Lobbes",
    "slug": "lobbes-6540",
    "zip": "6540",
    "province_name": "Hainaut",
    "province_code": "HT",
    "region": "Wallonie",
    "coordinates": {
      "lat": 50.35,
      "lng": 4.2667
    },
    "population": 5793
  },
  {
    "name": "Manage",
    "slug": "manage-7170",
    "zip": "7170",
    "province_name": "Hainaut",
    "province_code": "HT",
    "region": "Wallonie",
    "coordinates": {
      "lat": 50.5,
      "lng": 4.2333
    },
    "population": 23242
  },
  {
    "name": "Merbes-le-Château",
    "slug": "merbes-le-chateau-6567",
    "zip": "6567",
    "province_name": "Hainaut",
    "province_code": "HT",
    "region": "Wallonie",
    "coordinates": {
      "lat": 50.3167,
      "lng": 4.1667
    },
    "population": 4278
  },
  {
    "name": "Momignies",
    "slug": "momignies-6590",
    "zip": "6590",
    "province_name": "Hainaut",
    "province_code": "HT",
    "region": "Wallonie",
    "coordinates": {
      "lat": 50.0333,
      "lng": 4.1667
    },
    "population": 5300
  },
  {
    "name": "Mons",
    "slug": "mons-7000",
    "zip": "7000",
    "province_name": "Hainaut",
    "province_code": "HT",
    "region": "Wallonie",
    "coordinates": {
      "lat": 50.4541,
      "lng": 3.9567
    },
    "population": 95299
  },
  {
    "name": "Mont-de-l'Enclus",
    "slug": "mont-de-l-enclus-7750",
    "zip": "7750",
    "province_name": "Hainaut",
    "province_code": "HT",
    "region": "Wallonie",
    "coordinates": {
      "lat": 50.75,
      "lng": 3.5
    },
    "population": 3700
  },
  {
    "name": "Montigny-le-Tilleul",
    "slug": "montigny-le-tilleul-6110",
    "zip": "6110",
    "province_name": "Hainaut",
    "province_code": "HT",
    "region": "Wallonie",
    "coordinates": {
      "lat": 50.35,
      "lng": 4.3833
    },
    "population": 10489
  },
  {
    "name": "Morlanwelz",
    "slug": "morlanwelz-7140",
    "zip": "7140",
    "province_name": "Hainaut",
    "province_code": "HT",
    "region": "Wallonie",
    "coordinates": {
      "lat": 50.45,
      "lng": 4.2333
    },
    "population": 19200
  },
  {
    "name": "Mouscron",
    "slug": "mouscron-7700",
    "zip": "7700",
    "province_name": "Hainaut",
    "province_code": "HT",
    "region": "Wallonie",
    "coordinates": {
      "lat": 50.7444,
      "lng": 3.2064
    },
    "population": 58380
  },
  {
    "name": "Pecq",
    "slug": "pecq-7740",
    "zip": "7740",
    "province_name": "Hainaut",
    "province_code": "HT",
    "region": "Wallonie",
    "coordinates": {
      "lat": 50.6833,
      "lng": 3.3333
    },
    "population": 5700
  },
  {
    "name": "Pont-à-Celles",
    "slug": "pont-a-celles-6230",
    "zip": "6230",
    "province_name": "Hainaut",
    "province_code": "HT",
    "region": "Wallonie",
    "coordinates": {
      "lat": 50.5,
      "lng": 4.3667
    },
    "population": 17186
  },
  {
    "name": "Péruwelz",
    "slug": "peruwelz-7600",
    "zip": "7600",
    "province_name": "Hainaut",
    "province_code": "HT",
    "region": "Wallonie",
    "coordinates": {
      "lat": 50.5083,
      "lng": 3.5917
    },
    "population": 17279
  },
  {
    "name": "Quaregnon",
    "slug": "quaregnon-7390",
    "zip": "7390",
    "province_name": "Hainaut",
    "province_code": "HT",
    "region": "Wallonie",
    "coordinates": {
      "lat": 50.4431,
      "lng": 3.8667
    },
    "population": 19316
  },
  {
    "name": "Quiévrain",
    "slug": "quievrain-7380",
    "zip": "7380",
    "province_name": "Hainaut",
    "province_code": "HT",
    "region": "Wallonie",
    "coordinates": {
      "lat": 50.4,
      "lng": 3.6833
    },
    "population": 6800
  },
  {
    "name": "Quévy",
    "slug": "quevy-7040",
    "zip": "7040",
    "province_name": "Hainaut",
    "province_code": "HT",
    "region": "Wallonie",
    "coordinates": {
      "lat": 50.3667,
      "lng": 3.95
    },
    "population": 8000
  },
  {
    "name": "Rumes",
    "slug": "rumes-7610",
    "zip": "7610",
    "province_name": "Hainaut",
    "province_code": "HT",
    "region": "Wallonie",
    "coordinates": {
      "lat": 50.5333,
      "lng": 3.3
    },
    "population": 5200
  },
  {
    "name": "Saint-Ghislain",
    "slug": "saint-ghislain-7330",
    "zip": "7330",
    "province_name": "Hainaut",
    "province_code": "HT",
    "region": "Wallonie",
    "coordinates": {
      "lat": 50.45,
      "lng": 3.8167
    },
    "population": 23008
  },
  {
    "name": "Seneffe",
    "slug": "seneffe-7180",
    "zip": "7180",
    "province_name": "Hainaut",
    "province_code": "HT",
    "region": "Wallonie",
    "coordinates": {
      "lat": 50.5333,
      "lng": 4.2667
    },
    "population": 11333
  },
  {
    "name": "Silly",
    "slug": "silly-7830",
    "zip": "7830",
    "province_name": "Hainaut",
    "province_code": "HT",
    "region": "Wallonie",
    "coordinates": {
      "lat": 50.6333,
      "lng": 3.9167
    },
    "population": 8300
  },
  {
    "name": "Sivry-Rance",
    "slug": "sivry-rance-6470",
    "zip": "6470",
    "province_name": "Hainaut",
    "province_code": "HT",
    "region": "Wallonie",
    "coordinates": {
      "lat": 50.1333,
      "lng": 4.2167
    },
    "population": 5100
  },
  {
    "name": "Soignies",
    "slug": "soignies-7060",
    "zip": "7060",
    "province_name": "Hainaut",
    "province_code": "HT",
    "region": "Wallonie",
    "coordinates": {
      "lat": 50.5764,
      "lng": 4.0728
    },
    "population": 27967
  },
  {
    "name": "Thuin",
    "slug": "thuin-6530",
    "zip": "6530",
    "province_name": "Hainaut",
    "province_code": "HT",
    "region": "Wallonie",
    "coordinates": {
      "lat": 50.3392,
      "lng": 4.2861
    },
    "population": 14977
  },
  {
    "name": "Tournai",
    "slug": "tournai-7500",
    "zip": "7500",
    "province_name": "Hainaut",
    "province_code": "HT",
    "region": "Wallonie",
    "coordinates": {
      "lat": 50.6058,
      "lng": 3.3883
    },
    "population": 69554
  },
  {
    "name": "Amay",
    "slug": "amay-4540",
    "zip": "4540",
    "province_name": "Liège",
    "province_code": "LG",
    "region": "Wallonie",
    "coordinates": {
      "lat": 50.55,
      "lng": 5.3167
    },
    "population": 14379
  },
  {
    "name": "Ans",
    "slug": "ans-4430",
    "zip": "4430",
    "province_name": "Liège",
    "province_code": "LG",
    "region": "Wallonie",
    "coordinates": {
      "lat": 50.6667,
      "lng": 5.5167
    },
    "population": 28550
  },
  {
    "name": "Anthisnes",
    "slug": "anthisnes-4160",
    "zip": "4160",
    "province_name": "Liège",
    "province_code": "LG",
    "region": "Wallonie",
    "coordinates": {
      "lat": 50.4833,
      "lng": 5.5333
    },
    "population": 4200
  },
  {
    "name": "Aubel",
    "slug": "aubel-4880",
    "zip": "4880",
    "province_name": "Liège",
    "province_code": "LG",
    "region": "Wallonie",
    "coordinates": {
      "lat": 50.7,
      "lng": 5.85
    },
    "population": 4400
  },
  {
    "name": "Awans",
    "slug": "awans-4340",
    "zip": "4340",
    "province_name": "Liège",
    "province_code": "LG",
    "region": "Wallonie",
    "coordinates": {
      "lat": 50.6667,
      "lng": 5.4667
    },
    "population": 9200
  },
  {
    "name": "Aywaille",
    "slug": "aywaille-4920",
    "zip": "4920",
    "province_name": "Liège",
    "province_code": "LG",
    "region": "Wallonie",
    "coordinates": {
      "lat": 50.475,
      "lng": 5.675
    },
    "population": 12443
  },
  {
    "name": "Baelen",
    "slug": "baelen-4837",
    "zip": "4837",
    "province_name": "Liège",
    "province_code": "LG",
    "region": "Wallonie",
    "coordinates": {
      "lat": 50.6333,
      "lng": 5.9667
    },
    "population": 4400
  },
  {
    "name": "Bassenge",
    "slug": "bassenge-4690",
    "zip": "4690",
    "province_name": "Liège",
    "province_code": "LG",
    "region": "Wallonie",
    "coordinates": {
      "lat": 50.7667,
      "lng": 5.6167
    },
    "population": 8900
  },
  {
    "name": "Berloz",
    "slug": "berloz-4257",
    "zip": "4257",
    "province_name": "Liège",
    "province_code": "LG",
    "region": "Wallonie",
    "coordinates": {
      "lat": 50.7,
      "lng": 5.2167
    },
    "population": 3200
  },
  {
    "name": "Beyne-Heusay",
    "slug": "beyne-heusay-4610",
    "zip": "4610",
    "province_name": "Liège",
    "province_code": "LG",
    "region": "Wallonie",
    "coordinates": {
      "lat": 50.6167,
      "lng": 5.6667
    },
    "population": 12100
  },
  {
    "name": "Blegny",
    "slug": "blegny-4670",
    "zip": "4670",
    "province_name": "Liège",
    "province_code": "LG",
    "region": "Wallonie",
    "coordinates": {
      "lat": 50.6833,
      "lng": 5.7333
    },
    "population": 13200
  },
  {
    "name": "Braives",
    "slug": "braives-4260",
    "zip": "4260",
    "province_name": "Liège",
    "province_code": "LG",
    "region": "Wallonie",
    "coordinates": {
      "lat": 50.6333,
      "lng": 5.1667
    },
    "population": 6100
  },
  {
    "name": "Bullingen",
    "slug": "bullingen-4760",
    "zip": "4760",
    "province_name": "Liège",
    "province_code": "LG",
    "region": "Wallonie",
    "coordinates": {
      "lat": 50.4167,
      "lng": 6.25
    },
    "population": 5600
  },
  {
    "name": "Burdinne",
    "slug": "burdinne-4210",
    "zip": "4210",
    "province_name": "Liège",
    "province_code": "LG",
    "region": "Wallonie",
    "coordinates": {
      "lat": 50.5833,
      "lng": 5.0833
    },
    "population": 3100
  },
  {
    "name": "Burg-Reuland",
    "slug": "burg-reuland-4790",
    "zip": "4790",
    "province_name": "Liège",
    "province_code": "LG",
    "region": "Wallonie",
    "coordinates": {
      "lat": 50.2333,
      "lng": 6.1333
    },
    "population": 4000
  },
  {
    "name": "Bütgenbach",
    "slug": "butgenbach-4750",
    "zip": "4750",
    "province_name": "Liège",
    "province_code": "LG",
    "region": "Wallonie",
    "coordinates": {
      "lat": 50.4167,
      "lng": 6.2
    },
    "population": 5800
  },
  {
    "name": "Chaudfontaine",
    "slug": "chaudfontaine-4050",
    "zip": "4050",
    "province_name": "Liège",
    "province_code": "LG",
    "region": "Wallonie",
    "coordinates": {
      "lat": 50.5833,
      "lng": 5.65
    },
    "population": 21376
  },
  {
    "name": "Clavier",
    "slug": "clavier-4560",
    "zip": "4560",
    "province_name": "Liège",
    "province_code": "LG",
    "region": "Wallonie",
    "coordinates": {
      "lat": 50.4,
      "lng": 5.3667
    },
    "population": 4600
  },
  {
    "name": "Comblain-au-Pont",
    "slug": "comblain-au-pont-4170",
    "zip": "4170",
    "province_name": "Liège",
    "province_code": "LG",
    "region": "Wallonie",
    "coordinates": {
      "lat": 50.4667,
      "lng": 5.5833
    },
    "population": 5400
  },
  {
    "name": "Crisnée",
    "slug": "crisnee-4367",
    "zip": "4367",
    "province_name": "Liège",
    "province_code": "LG",
    "region": "Wallonie",
    "coordinates": {
      "lat": 50.7,
      "lng": 5.5
    },
    "population": 3100
  },
  {
    "name": "Dalhem",
    "slug": "dalhem-4607",
    "zip": "4607",
    "province_name": "Liège",
    "province_code": "LG",
    "region": "Wallonie",
    "coordinates": {
      "lat": 50.7,
      "lng": 5.7333
    },
    "population": 7200
  },
  {
    "name": "Dison",
    "slug": "dison-4820",
    "zip": "4820",
    "province_name": "Liège",
    "province_code": "LG",
    "region": "Wallonie",
    "coordinates": {
      "lat": 50.6117,
      "lng": 5.8544
    },
    "population": 15590
  },
  {
    "name": "Donceel",
    "slug": "donceel-4357",
    "zip": "4357",
    "province_name": "Liège",
    "province_code": "LG",
    "region": "Wallonie",
    "coordinates": {
      "lat": 50.6667,
      "lng": 5.35
    },
    "population": 3000
  },
  {
    "name": "Engis",
    "slug": "engis-4480",
    "zip": "4480",
    "province_name": "Liège",
    "province_code": "LG",
    "region": "Wallonie",
    "coordinates": {
      "lat": 50.5833,
      "lng": 5.3833
    },
    "population": 6100
  },
  {
    "name": "Esneux",
    "slug": "esneux-4130",
    "zip": "4130",
    "province_name": "Liège",
    "province_code": "LG",
    "region": "Wallonie",
    "coordinates": {
      "lat": 50.5333,
      "lng": 5.5667
    },
    "population": 13100
  },
  {
    "name": "Eupen",
    "slug": "eupen-4700",
    "zip": "4700",
    "province_name": "Liège",
    "province_code": "LG",
    "region": "Wallonie",
    "coordinates": {
      "lat": 50.6275,
      "lng": 6.0361
    },
    "population": 19892
  },
  {
    "name": "Faimes",
    "slug": "faimes-4317",
    "zip": "4317",
    "province_name": "Liège",
    "province_code": "LG",
    "region": "Wallonie",
    "coordinates": {
      "lat": 50.6833,
      "lng": 5.2667
    },
    "population": 3800
  },
  {
    "name": "Ferrières",
    "slug": "ferrieres-4190",
    "zip": "4190",
    "province_name": "Liège",
    "province_code": "LG",
    "region": "Wallonie",
    "coordinates": {
      "lat": 50.4,
      "lng": 5.6167
    },
    "population": 4800
  },
  {
    "name": "Fexhe-le-Haut-Clocher",
    "slug": "fexhe-le-haut-clocher-4347",
    "zip": "4347",
    "province_name": "Liège",
    "province_code": "LG",
    "region": "Wallonie",
    "coordinates": {
      "lat": 50.6833,
      "lng": 5.3833
    },
    "population": 3400
  },
  {
    "name": "Flémalle",
    "slug": "flemalle-4400",
    "zip": "4400",
    "province_name": "Liège",
    "province_code": "LG",
    "region": "Wallonie",
    "coordinates": {
      "lat": 50.6,
      "lng": 5.4667
    },
    "population": 26500
  },
  {
    "name": "Fléron",
    "slug": "fleron-4620",
    "zip": "4620",
    "province_name": "Liège",
    "province_code": "LG",
    "region": "Wallonie",
    "coordinates": {
      "lat": 50.6167,
      "lng": 5.6833
    },
    "population": 16834
  },
  {
    "name": "Geer",
    "slug": "geer-4250",
    "zip": "4250",
    "province_name": "Liège",
    "province_code": "LG",
    "region": "Wallonie",
    "coordinates": {
      "lat": 50.6667,
      "lng": 5.1833
    },
    "population": 3400
  },
  {
    "name": "Grâce-Hollogne",
    "slug": "grace-hollogne-4460",
    "zip": "4460",
    "province_name": "Liège",
    "province_code": "LG",
    "region": "Wallonie",
    "coordinates": {
      "lat": 50.6333,
      "lng": 5.5
    },
    "population": 22500
  },
  {
    "name": "Hamoir",
    "slug": "hamoir-4180",
    "zip": "4180",
    "province_name": "Liège",
    "province_code": "LG",
    "region": "Wallonie",
    "coordinates": {
      "lat": 50.4333,
      "lng": 5.5333
    },
    "population": 3800
  },
  {
    "name": "Hannut",
    "slug": "hannut-4280",
    "zip": "4280",
    "province_name": "Liège",
    "province_code": "LG",
    "region": "Wallonie",
    "coordinates": {
      "lat": 50.6717,
      "lng": 5.0783
    },
    "population": 16137
  },
  {
    "name": "Herstal",
    "slug": "herstal-4040",
    "zip": "4040",
    "province_name": "Liège",
    "province_code": "LG",
    "region": "Wallonie",
    "coordinates": {
      "lat": 50.6667,
      "lng": 5.6333
    },
    "population": 39689
  },
  {
    "name": "Huy",
    "slug": "huy-4500",
    "zip": "4500",
    "province_name": "Liège",
    "province_code": "LG",
    "region": "Wallonie",
    "coordinates": {
      "lat": 50.5167,
      "lng": 5.2333
    },
    "population": 21573
  },
  {
    "name": "Héron",
    "slug": "heron-4217",
    "zip": "4217",
    "province_name": "Liège",
    "province_code": "LG",
    "region": "Wallonie",
    "coordinates": {
      "lat": 50.55,
      "lng": 5.1
    },
    "population": 5200
  },
  {
    "name": "Jalhay",
    "slug": "jalhay-4845",
    "zip": "4845",
    "province_name": "Liège",
    "province_code": "LG",
    "region": "Wallonie",
    "coordinates": {
      "lat": 50.55,
      "lng": 5.9667
    },
    "population": 8600
  },
  {
    "name": "Juprelle",
    "slug": "juprelle-4450",
    "zip": "4450",
    "province_name": "Liège",
    "province_code": "LG",
    "region": "Wallonie",
    "coordinates": {
      "lat": 50.7167,
      "lng": 5.5333
    },
    "population": 9500
  },
  {
    "name": "Kelmis",
    "slug": "kelmis-4720",
    "zip": "4720",
    "province_name": "Liège",
    "province_code": "LG",
    "region": "Wallonie",
    "coordinates": {
      "lat": 50.7167,
      "lng": 6.0167
    },
    "population": 11200
  },
  {
    "name": "Lierneux",
    "slug": "lierneux-4990",
    "zip": "4990",
    "province_name": "Liège",
    "province_code": "LG",
    "region": "Wallonie",
    "coordinates": {
      "lat": 50.2833,
      "lng": 5.7833
    },
    "population": 3600
  },
  {
    "name": "Limbourg",
    "slug": "limbourg-4830",
    "zip": "4830",
    "province_name": "Liège",
    "province_code": "LG",
    "region": "Wallonie",
    "coordinates": {
      "lat": 50.6167,
      "lng": 5.9333
    },
    "population": 5800
  },
  {
    "name": "Liège",
    "slug": "liege-4000",
    "zip": "4000",
    "province_name": "Liège",
    "province_code": "LG",
    "region": "Wallonie",
    "coordinates": {
      "lat": 50.6326,
      "lng": 5.5797
    },
    "population": 197013
  },
  {
    "name": "Lontzen",
    "slug": "lontzen-4710",
    "zip": "4710",
    "province_name": "Liège",
    "province_code": "LG",
    "region": "Wallonie",
    "coordinates": {
      "lat": 50.6833,
      "lng": 6.0
    },
    "population": 5700
  },
  {
    "name": "Malmedy",
    "slug": "malmedy-4960",
    "zip": "4960",
    "province_name": "Liège",
    "province_code": "LG",
    "region": "Wallonie",
    "coordinates": {
      "lat": 50.4256,
      "lng": 6.0278
    },
    "population": 12644
  },
  {
    "name": "Marchin",
    "slug": "marchin-4570",
    "zip": "4570",
    "province_name": "Liège",
    "province_code": "LG",
    "region": "Wallonie",
    "coordinates": {
      "lat": 50.4667,
      "lng": 5.25
    },
    "population": 5500
  },
  {
    "name": "Modave",
    "slug": "modave-4577",
    "zip": "4577",
    "province_name": "Liège",
    "province_code": "LG",
    "region": "Wallonie",
    "coordinates": {
      "lat": 50.45,
      "lng": 5.3
    },
    "population": 4100
  },
  {
    "name": "Nandrin",
    "slug": "nandrin-4550",
    "zip": "4550",
    "province_name": "Liège",
    "province_code": "LG",
    "region": "Wallonie",
    "coordinates": {
      "lat": 50.5167,
      "lng": 5.4167
    },
    "population": 5800
  },
  {
    "name": "Neupré",
    "slug": "neupre-4120",
    "zip": "4120",
    "province_name": "Liège",
    "province_code": "LG",
    "region": "Wallonie",
    "coordinates": {
      "lat": 50.55,
      "lng": 5.5
    },
    "population": 10100
  },
  {
    "name": "Olne",
    "slug": "olne-4877",
    "zip": "4877",
    "province_name": "Liège",
    "province_code": "LG",
    "region": "Wallonie",
    "coordinates": {
      "lat": 50.5833,
      "lng": 5.75
    },
    "population": 4000
  },
  {
    "name": "Ouffet",
    "slug": "ouffet-4590",
    "zip": "4590",
    "province_name": "Liège",
    "province_code": "LG",
    "region": "Wallonie",
    "coordinates": {
      "lat": 50.4333,
      "lng": 5.45
    },
    "population": 2800
  },
  {
    "name": "Oupeye",
    "slug": "oupeye-4680",
    "zip": "4680",
    "province_name": "Liège",
    "province_code": "LG",
    "region": "Wallonie",
    "coordinates": {
      "lat": 50.7083,
      "lng": 5.65
    },
    "population": 24655
  },
  {
    "name": "Pepinster",
    "slug": "pepinster-4860",
    "zip": "4860",
    "province_name": "Liège",
    "province_code": "LG",
    "region": "Wallonie",
    "coordinates": {
      "lat": 50.5708,
      "lng": 5.8003
    },
    "population": 9961
  },
  {
    "name": "Plombières",
    "slug": "plombieres-4850",
    "zip": "4850",
    "province_name": "Liège",
    "province_code": "LG",
    "region": "Wallonie",
    "coordinates": {
      "lat": 50.7333,
      "lng": 5.9667
    },
    "population": 10200
  },
  {
    "name": "Raeren",
    "slug": "raeren-4730",
    "zip": "4730",
    "province_name": "Liège",
    "province_code": "LG",
    "region": "Wallonie",
    "coordinates": {
      "lat": 50.6667,
      "lng": 6.1
    },
    "population": 11000
  },
  {
    "name": "Remicourt",
    "slug": "remicourt-4350",
    "zip": "4350",
    "province_name": "Liège",
    "province_code": "LG",
    "region": "Wallonie",
    "coordinates": {
      "lat": 50.6667,
      "lng": 5.3167
    },
    "population": 5800
  },
  {
    "name": "Saint-Georges-sur-Meuse",
    "slug": "saint-georges-sur-meuse-4470",
    "zip": "4470",
    "province_name": "Liège",
    "province_code": "LG",
    "region": "Wallonie",
    "coordinates": {
      "lat": 50.5833,
      "lng": 5.4
    },
    "population": 6900
  },
  {
    "name": "Saint-Nicolas",
    "slug": "saint-nicolas-4420",
    "zip": "4420",
    "province_name": "Liège",
    "province_code": "LG",
    "region": "Wallonie",
    "coordinates": {
      "lat": 50.6333,
      "lng": 5.5333
    },
    "population": 24246
  },
  {
    "name": "Sankt Vith",
    "slug": "sankt-vith-4780",
    "zip": "4780",
    "province_name": "Liège",
    "province_code": "LG",
    "region": "Wallonie",
    "coordinates": {
      "lat": 50.2833,
      "lng": 6.1333
    },
    "population": 9800
  },
  {
    "name": "Seraing",
    "slug": "seraing-4100",
    "zip": "4100",
    "province_name": "Liège",
    "province_code": "LG",
    "region": "Wallonie",
    "coordinates": {
      "lat": 50.5833,
      "lng": 5.5
    },
    "population": 64056
  },
  {
    "name": "Soumagne",
    "slug": "soumagne-4630",
    "zip": "4630",
    "province_name": "Liège",
    "province_code": "LG",
    "region": "Wallonie",
    "coordinates": {
      "lat": 50.6167,
      "lng": 5.75
    },
    "population": 16500
  },
  {
    "name": "Spa",
    "slug": "spa-4900",
    "zip": "4900",
    "province_name": "Liège",
    "province_code": "LG",
    "region": "Wallonie",
    "coordinates": {
      "lat": 50.4833,
      "lng": 5.8667
    },
    "population": 10543
  },
  {
    "name": "Sprimont",
    "slug": "sprimont-4140",
    "zip": "4140",
    "province_name": "Liège",
    "province_code": "LG",
    "region": "Wallonie",
    "coordinates": {
      "lat": 50.5,
      "lng": 5.6667
    },
    "population": 14777
  },
  {
    "name": "Stavelot",
    "slug": "stavelot-4970",
    "zip": "4970",
    "province_name": "Liège",
    "province_code": "LG",
    "region": "Wallonie",
    "coordinates": {
      "lat": 50.395,
      "lng": 5.9317
    },
    "population": 7163
  },
  {
    "name": "Stoumont",
    "slug": "stoumont-4987",
    "zip": "4987",
    "province_name": "Liège",
    "province_code": "LG",
    "region": "Wallonie",
    "coordinates": {
      "lat": 50.3833,
      "lng": 5.8167
    },
    "population": 3200
  },
  {
    "name": "Theux",
    "slug": "theux-4910",
    "zip": "4910",
    "province_name": "Liège",
    "province_code": "LG",
    "region": "Wallonie",
    "coordinates": {
      "lat": 50.5333,
      "lng": 5.8167
    },
    "population": 12200
  },
  {
    "name": "Thimister-Clermont",
    "slug": "thimister-clermont-4890",
    "zip": "4890",
    "province_name": "Liège",
    "province_code": "LG",
    "region": "Wallonie",
    "coordinates": {
      "lat": 50.65,
      "lng": 5.85
    },
    "population": 5600
  },
  {
    "name": "Tinlot",
    "slug": "tinlot-4557",
    "zip": "4557",
    "province_name": "Liège",
    "province_code": "LG",
    "region": "Wallonie",
    "coordinates": {
      "lat": 50.4833,
      "lng": 5.3667
    },
    "population": 2700
  },
  {
    "name": "Trois-Ponts",
    "slug": "trois-ponts-4980",
    "zip": "4980",
    "province_name": "Liège",
    "province_code": "LG",
    "region": "Wallonie",
    "coordinates": {
      "lat": 50.3667,
      "lng": 5.8667
    },
    "population": 2600
  },
  {
    "name": "Trooz",
    "slug": "trooz-4870",
    "zip": "4870",
    "province_name": "Liège",
    "province_code": "LG",
    "region": "Wallonie",
    "coordinates": {
      "lat": 50.5667,
      "lng": 5.7
    },
    "population": 8400
  },
  {
    "name": "Verlaine",
    "slug": "verlaine-4537",
    "zip": "4537",
    "province_name": "Liège",
    "province_code": "LG",
    "region": "Wallonie",
    "coordinates": {
      "lat": 50.5833,
      "lng": 5.3167
    },
    "population": 4200
  },
  {
    "name": "Verviers",
    "slug": "verviers-4800",
    "zip": "4800",
    "province_name": "Liège",
    "province_code": "LG",
    "region": "Wallonie",
    "coordinates": {
      "lat": 50.588,
      "lng": 5.8624
    },
    "population": 55602
  },
  {
    "name": "Villers-le-Bouillet",
    "slug": "villers-le-bouillet-4530",
    "zip": "4530",
    "province_name": "Liège",
    "province_code": "LG",
    "region": "Wallonie",
    "coordinates": {
      "lat": 50.5667,
      "lng": 5.2833
    },
    "population": 6500
  },
  {
    "name": "Visé",
    "slug": "vise-4600",
    "zip": "4600",
    "province_name": "Liège",
    "province_code": "LG",
    "region": "Wallonie",
    "coordinates": {
      "lat": 50.7333,
      "lng": 5.7
    },
    "population": 18254
  },
  {
    "name": "Wanze",
    "slug": "wanze-4520",
    "zip": "4520",
    "province_name": "Liège",
    "province_code": "LG",
    "region": "Wallonie",
    "coordinates": {
      "lat": 50.5333,
      "lng": 5.2
    },
    "population": 13600
  },
  {
    "name": "Waremme",
    "slug": "waremme-4300",
    "zip": "4300",
    "province_name": "Liège",
    "province_code": "LG",
    "region": "Wallonie",
    "coordinates": {
      "lat": 50.6967,
      "lng": 5.255
    },
    "population": 15793
  },
  {
    "name": "Wasseiges",
    "slug": "wasseiges-4219",
    "zip": "4219",
    "province_name": "Liège",
    "province_code": "LG",
    "region": "Wallonie",
    "coordinates": {
      "lat": 50.6167,
      "lng": 5.0
    },
    "population": 2800
  },
  {
    "name": "Welkenraedt",
    "slug": "welkenraedt-4840",
    "zip": "4840",
    "province_name": "Liège",
    "province_code": "LG",
    "region": "Wallonie",
    "coordinates": {
      "lat": 50.6667,
      "lng": 5.9667
    },
    "population": 10000
  },
  {
    "name": "Arlon",
    "slug": "arlon-6700",
    "zip": "6700",
    "province_name": "Luxembourg",
    "province_code": "LX",
    "region": "Wallonie",
    "coordinates": {
      "lat": 49.6833,
      "lng": 5.8167
    },
    "population": 30753
  },
  {
    "name": "Attert",
    "slug": "attert-6717",
    "zip": "6717",
    "province_name": "Luxembourg",
    "province_code": "LX",
    "region": "Wallonie",
    "coordinates": {
      "lat": 49.75,
      "lng": 5.7833
    },
    "population": 5500
  },
  {
    "name": "Aubange",
    "slug": "aubange-6790",
    "zip": "6790",
    "province_name": "Luxembourg",
    "province_code": "LX",
    "region": "Wallonie",
    "coordinates": {
      "lat": 49.5667,
      "lng": 5.8
    },
    "population": 17248
  },
  {
    "name": "Bastogne",
    "slug": "bastogne-6600",
    "zip": "6600",
    "province_name": "Luxembourg",
    "province_code": "LX",
    "region": "Wallonie",
    "coordinates": {
      "lat": 50.0,
      "lng": 5.7167
    },
    "population": 16250
  },
  {
    "name": "Bertogne",
    "slug": "bertogne-6687",
    "zip": "6687",
    "province_name": "Luxembourg",
    "province_code": "LX",
    "region": "Wallonie",
    "coordinates": {
      "lat": 50.0833,
      "lng": 5.6667
    },
    "population": 3500
  },
  {
    "name": "Bertrix",
    "slug": "bertrix-6880",
    "zip": "6880",
    "province_name": "Luxembourg",
    "province_code": "LX",
    "region": "Wallonie",
    "coordinates": {
      "lat": 49.85,
      "lng": 5.2667
    },
    "population": 8803
  },
  {
    "name": "Bouillon",
    "slug": "bouillon-6830",
    "zip": "6830",
    "province_name": "Luxembourg",
    "province_code": "LX",
    "region": "Wallonie",
    "coordinates": {
      "lat": 49.7933,
      "lng": 5.0672
    },
    "population": 5487
  },
  {
    "name": "Chiny",
    "slug": "chiny-6810",
    "zip": "6810",
    "province_name": "Luxembourg",
    "province_code": "LX",
    "region": "Wallonie",
    "coordinates": {
      "lat": 49.7333,
      "lng": 5.3333
    },
    "population": 5200
  },
  {
    "name": "Daverdisse",
    "slug": "daverdisse-6929",
    "zip": "6929",
    "province_name": "Luxembourg",
    "province_code": "LX",
    "region": "Wallonie",
    "coordinates": {
      "lat": 50.0167,
      "lng": 5.1167
    },
    "population": 1500
  },
  {
    "name": "Durbuy",
    "slug": "durbuy-6940",
    "zip": "6940",
    "province_name": "Luxembourg",
    "province_code": "LX",
    "region": "Wallonie",
    "coordinates": {
      "lat": 50.3531,
      "lng": 5.4564
    },
    "population": 11466
  },
  {
    "name": "Erezée",
    "slug": "erezee-6997",
    "zip": "6997",
    "province_name": "Luxembourg",
    "province_code": "LX",
    "region": "Wallonie",
    "coordinates": {
      "lat": 50.3,
      "lng": 5.55
    },
    "population": 3200
  },
  {
    "name": "Fauvillers",
    "slug": "fauvillers-6637",
    "zip": "6637",
    "province_name": "Luxembourg",
    "province_code": "LX",
    "region": "Wallonie",
    "coordinates": {
      "lat": 49.8833,
      "lng": 5.6
    },
    "population": 2300
  },
  {
    "name": "Florenville",
    "slug": "florenville-6820",
    "zip": "6820",
    "province_name": "Luxembourg",
    "province_code": "LX",
    "region": "Wallonie",
    "coordinates": {
      "lat": 49.6992,
      "lng": 5.3058
    },
    "population": 5627
  },
  {
    "name": "Gouvy",
    "slug": "gouvy-6670",
    "zip": "6670",
    "province_name": "Luxembourg",
    "province_code": "LX",
    "region": "Wallonie",
    "coordinates": {
      "lat": 50.1833,
      "lng": 5.95
    },
    "population": 5300
  },
  {
    "name": "Habay",
    "slug": "habay-6720",
    "zip": "6720",
    "province_name": "Luxembourg",
    "province_code": "LX",
    "region": "Wallonie",
    "coordinates": {
      "lat": 49.7167,
      "lng": 5.6333
    },
    "population": 8574
  },
  {
    "name": "Herbeumont",
    "slug": "herbeumont-6887",
    "zip": "6887",
    "province_name": "Luxembourg",
    "province_code": "LX",
    "region": "Wallonie",
    "coordinates": {
      "lat": 49.7833,
      "lng": 5.2333
    },
    "population": 1700
  },
  {
    "name": "Hotton",
    "slug": "hotton-6990",
    "zip": "6990",
    "province_name": "Luxembourg",
    "province_code": "LX",
    "region": "Wallonie",
    "coordinates": {
      "lat": 50.2667,
      "lng": 5.45
    },
    "population": 5730
  },
  {
    "name": "Houffalize",
    "slug": "houffalize-6660",
    "zip": "6660",
    "province_name": "Luxembourg",
    "province_code": "LX",
    "region": "Wallonie",
    "coordinates": {
      "lat": 50.1333,
      "lng": 5.7833
    },
    "population": 5200
  },
  {
    "name": "La Roche-en-Ardenne",
    "slug": "la-roche-en-ardenne-6980",
    "zip": "6980",
    "province_name": "Luxembourg",
    "province_code": "LX",
    "region": "Wallonie",
    "coordinates": {
      "lat": 50.1833,
      "lng": 5.5833
    },
    "population": 4320
  },
  {
    "name": "Libramont-Chevigny",
    "slug": "libramont-chevigny-6800",
    "zip": "6800",
    "province_name": "Luxembourg",
    "province_code": "LX",
    "region": "Wallonie",
    "coordinates": {
      "lat": 49.9167,
      "lng": 5.3833
    },
    "population": 11346
  },
  {
    "name": "Léglise",
    "slug": "leglise-6860",
    "zip": "6860",
    "province_name": "Luxembourg",
    "province_code": "LX",
    "region": "Wallonie",
    "coordinates": {
      "lat": 49.8,
      "lng": 5.55
    },
    "population": 5300
  },
  {
    "name": "Manhay",
    "slug": "manhay-6960",
    "zip": "6960",
    "province_name": "Luxembourg",
    "province_code": "LX",
    "region": "Wallonie",
    "coordinates": {
      "lat": 50.2833,
      "lng": 5.6833
    },
    "population": 3600
  },
  {
    "name": "Marche-en-Famenne",
    "slug": "marche-en-famenne-6900",
    "zip": "6900",
    "province_name": "Luxembourg",
    "province_code": "LX",
    "region": "Wallonie",
    "coordinates": {
      "lat": 50.2272,
      "lng": 5.3444
    },
    "population": 17735
  },
  {
    "name": "Meix-devant-Virton",
    "slug": "meix-devant-virton-6769",
    "zip": "6769",
    "province_name": "Luxembourg",
    "province_code": "LX",
    "region": "Wallonie",
    "coordinates": {
      "lat": 49.6167,
      "lng": 5.5
    },
    "population": 2900
  },
  {
    "name": "Messancy",
    "slug": "messancy-6780",
    "zip": "6780",
    "province_name": "Luxembourg",
    "province_code": "LX",
    "region": "Wallonie",
    "coordinates": {
      "lat": 49.5833,
      "lng": 5.8167
    },
    "population": 8500
  },
  {
    "name": "Musson",
    "slug": "musson-6750",
    "zip": "6750",
    "province_name": "Luxembourg",
    "province_code": "LX",
    "region": "Wallonie",
    "coordinates": {
      "lat": 49.5667,
      "lng": 5.7
    },
    "population": 4500
  },
  {
    "name": "Nassogne",
    "slug": "nassogne-6950",
    "zip": "6950",
    "province_name": "Luxembourg",
    "province_code": "LX",
    "region": "Wallonie",
    "coordinates": {
      "lat": 50.1333,
      "lng": 5.35
    },
    "population": 5500
  },
  {
    "name": "Neufchâteau",
    "slug": "neufchateau-6840",
    "zip": "6840",
    "province_name": "Luxembourg",
    "province_code": "LX",
    "region": "Wallonie",
    "coordinates": {
      "lat": 49.8417,
      "lng": 5.4333
    },
    "population": 8056
  },
  {
    "name": "Paliseul",
    "slug": "paliseul-6850",
    "zip": "6850",
    "province_name": "Luxembourg",
    "province_code": "LX",
    "region": "Wallonie",
    "coordinates": {
      "lat": 49.9,
      "lng": 5.1333
    },
    "population": 5400
  },
  {
    "name": "Rendeux",
    "slug": "rendeux-6987",
    "zip": "6987",
    "province_name": "Luxembourg",
    "province_code": "LX",
    "region": "Wallonie",
    "coordinates": {
      "lat": 50.2333,
      "lng": 5.5
    },
    "population": 2600
  },
  {
    "name": "Rouvroy",
    "slug": "rouvroy-6767",
    "zip": "6767",
    "province_name": "Luxembourg",
    "province_code": "LX",
    "region": "Wallonie",
    "coordinates": {
      "lat": 49.55,
      "lng": 5.4833
    },
    "population": 2200
  },
  {
    "name": "Saint-Hubert",
    "slug": "saint-hubert-6870",
    "zip": "6870",
    "province_name": "Luxembourg",
    "province_code": "LX",
    "region": "Wallonie",
    "coordinates": {
      "lat": 50.0333,
      "lng": 5.3833
    },
    "population": 5800
  },
  {
    "name": "Saint-Léger",
    "slug": "saint-leger-6747",
    "zip": "6747",
    "province_name": "Luxembourg",
    "province_code": "LX",
    "region": "Wallonie",
    "coordinates": {
      "lat": 49.6167,
      "lng": 5.65
    },
    "population": 3700
  },
  {
    "name": "Sainte-Ode",
    "slug": "sainte-ode-6680",
    "zip": "6680",
    "province_name": "Luxembourg",
    "province_code": "LX",
    "region": "Wallonie",
    "coordinates": {
      "lat": 50.0167,
      "lng": 5.5333
    },
    "population": 2700
  },
  {
    "name": "Tellin",
    "slug": "tellin-6927",
    "zip": "6927",
    "province_name": "Luxembourg",
    "province_code": "LX",
    "region": "Wallonie",
    "coordinates": {
      "lat": 50.0667,
      "lng": 5.2167
    },
    "population": 2500
  },
  {
    "name": "Tenneville",
    "slug": "tenneville-6970",
    "zip": "6970",
    "province_name": "Luxembourg",
    "province_code": "LX",
    "region": "Wallonie",
    "coordinates": {
      "lat": 50.1,
      "lng": 5.5333
    },
    "population": 2900
  },
  {
    "name": "Tintigny",
    "slug": "tintigny-6730",
    "zip": "6730",
    "province_name": "Luxembourg",
    "province_code": "LX",
    "region": "Wallonie",
    "coordinates": {
      "lat": 49.6833,
      "lng": 5.5167
    },
    "population": 4200
  },
  {
    "name": "Vaux-sur-Sûre",
    "slug": "vaux-sur-sure-6640",
    "zip": "6640",
    "province_name": "Luxembourg",
    "province_code": "LX",
    "region": "Wallonie",
    "coordinates": {
      "lat": 49.9167,
      "lng": 5.6167
    },
    "population": 5100
  },
  {
    "name": "Vielsalm",
    "slug": "vielsalm-6690",
    "zip": "6690",
    "province_name": "Luxembourg",
    "province_code": "LX",
    "region": "Wallonie",
    "coordinates": {
      "lat": 50.2833,
      "lng": 5.9167
    },
    "population": 7800
  },
  {
    "name": "Virton",
    "slug": "virton-6760",
    "zip": "6760",
    "province_name": "Luxembourg",
    "province_code": "LX",
    "region": "Wallonie",
    "coordinates": {
      "lat": 49.5667,
      "lng": 5.5333
    },
    "population": 11838
  },
  {
    "name": "Wellin",
    "slug": "wellin-6920",
    "zip": "6920",
    "province_name": "Luxembourg",
    "province_code": "LX",
    "region": "Wallonie",
    "coordinates": {
      "lat": 50.0833,
      "lng": 5.1167
    },
    "population": 3100
  },
  {
    "name": "Étalle",
    "slug": "etalle-6740",
    "zip": "6740",
    "province_name": "Luxembourg",
    "province_code": "LX",
    "region": "Wallonie",
    "coordinates": {
      "lat": 49.6667,
      "lng": 5.6
    },
    "population": 5800
  },
  {
    "name": "Andenne",
    "slug": "andenne-5300",
    "zip": "5300",
    "province_name": "Namur",
    "province_code": "NA",
    "region": "Wallonie",
    "coordinates": {
      "lat": 50.4903,
      "lng": 5.0958
    },
    "population": 27596
  },
  {
    "name": "Anhée",
    "slug": "anhee-5537",
    "zip": "5537",
    "province_name": "Namur",
    "province_code": "NA",
    "region": "Wallonie",
    "coordinates": {
      "lat": 50.3167,
      "lng": 4.8667
    },
    "population": 7200
  },
  {
    "name": "Assesse",
    "slug": "assesse-5330",
    "zip": "5330",
    "province_name": "Namur",
    "province_code": "NA",
    "region": "Wallonie",
    "coordinates": {
      "lat": 50.3667,
      "lng": 4.9833
    },
    "population": 7000
  },
  {
    "name": "Beauraing",
    "slug": "beauraing-5570",
    "zip": "5570",
    "province_name": "Namur",
    "province_code": "NA",
    "region": "Wallonie",
    "coordinates": {
      "lat": 50.1167,
      "lng": 4.9667
    },
    "population": 9200
  },
  {
    "name": "Bièvre",
    "slug": "bievre-5555",
    "zip": "5555",
    "province_name": "Namur",
    "province_code": "NA",
    "region": "Wallonie",
    "coordinates": {
      "lat": 49.95,
      "lng": 5.0
    },
    "population": 3400
  },
  {
    "name": "Ciney",
    "slug": "ciney-5590",
    "zip": "5590",
    "province_name": "Namur",
    "province_code": "NA",
    "region": "Wallonie",
    "coordinates": {
      "lat": 50.2936,
      "lng": 5.1028
    },
    "population": 16656
  },
  {
    "name": "Couvin",
    "slug": "couvin-5660",
    "zip": "5660",
    "province_name": "Namur",
    "province_code": "NA",
    "region": "Wallonie",
    "coordinates": {
      "lat": 50.0536,
      "lng": 4.4931
    },
    "population": 13998
  },
  {
    "name": "Dinant",
    "slug": "dinant-5500",
    "zip": "5500",
    "province_name": "Namur",
    "province_code": "NA",
    "region": "Wallonie",
    "coordinates": {
      "lat": 50.2628,
      "lng": 4.9119
    },
    "population": 13739
  },
  {
    "name": "Doische",
    "slug": "doische-5680",
    "zip": "5680",
    "province_name": "Namur",
    "province_code": "NA",
    "region": "Wallonie",
    "coordinates": {
      "lat": 50.1,
      "lng": 4.7333
    },
    "population": 2900
  },
  {
    "name": "Fernelmont",
    "slug": "fernelmont-5380",
    "zip": "5380",
    "province_name": "Namur",
    "province_code": "NA",
    "region": "Wallonie",
    "coordinates": {
      "lat": 50.5333,
      "lng": 4.9667
    },
    "population": 7600
  },
  {
    "name": "Floreffe",
    "slug": "floreffe-5150",
    "zip": "5150",
    "province_name": "Namur",
    "province_code": "NA",
    "region": "Wallonie",
    "coordinates": {
      "lat": 50.4333,
      "lng": 4.7667
    },
    "population": 8006
  },
  {
    "name": "Fosses-la-Ville",
    "slug": "fosses-la-ville-5070",
    "zip": "5070",
    "province_name": "Namur",
    "province_code": "NA",
    "region": "Wallonie",
    "coordinates": {
      "lat": 50.3917,
      "lng": 4.6917
    },
    "population": 9964
  },
  {
    "name": "Gedinne",
    "slug": "gedinne-5575",
    "zip": "5575",
    "province_name": "Namur",
    "province_code": "NA",
    "region": "Wallonie",
    "coordinates": {
      "lat": 49.9833,
      "lng": 4.9333
    },
    "population": 4600
  },
  {
    "name": "Gembloux",
    "slug": "gembloux-5030",
    "zip": "5030",
    "province_name": "Namur",
    "province_code": "NA",
    "region": "Wallonie",
    "coordinates": {
      "lat": 50.5608,
      "lng": 4.6944
    },
    "population": 25186
  },
  {
    "name": "Gesves",
    "slug": "gesves-5340",
    "zip": "5340",
    "province_name": "Namur",
    "province_code": "NA",
    "region": "Wallonie",
    "coordinates": {
      "lat": 50.4,
      "lng": 5.0667
    },
    "population": 7100
  },
  {
    "name": "Hamois",
    "slug": "hamois-5360",
    "zip": "5360",
    "province_name": "Namur",
    "province_code": "NA",
    "region": "Wallonie",
    "coordinates": {
      "lat": 50.3333,
      "lng": 5.15
    },
    "population": 7100
  },
  {
    "name": "Hastière",
    "slug": "hastiere-5540",
    "zip": "5540",
    "province_name": "Namur",
    "province_code": "NA",
    "region": "Wallonie",
    "coordinates": {
      "lat": 50.2167,
      "lng": 4.8333
    },
    "population": 5900
  },
  {
    "name": "Havelange",
    "slug": "havelange-5370",
    "zip": "5370",
    "province_name": "Namur",
    "province_code": "NA",
    "region": "Wallonie",
    "coordinates": {
      "lat": 50.3833,
      "lng": 5.2333
    },
    "population": 5100
  },
  {
    "name": "Houyet",
    "slug": "houyet-5560",
    "zip": "5560",
    "province_name": "Namur",
    "province_code": "NA",
    "region": "Wallonie",
    "coordinates": {
      "lat": 50.1833,
      "lng": 5.0167
    },
    "population": 4800
  },
  {
    "name": "Jemeppe-sur-Sambre",
    "slug": "jemeppe-sur-sambre-5190",
    "zip": "5190",
    "province_name": "Namur",
    "province_code": "NA",
    "region": "Wallonie",
    "coordinates": {
      "lat": 50.4333,
      "lng": 4.6667
    },
    "population": 19000
  },
  {
    "name": "La Bruyère",
    "slug": "la-bruyere-5080",
    "zip": "5080",
    "province_name": "Namur",
    "province_code": "NA",
    "region": "Wallonie",
    "coordinates": {
      "lat": 50.5,
      "lng": 4.7833
    },
    "population": 9200
  },
  {
    "name": "Mettet",
    "slug": "mettet-5640",
    "zip": "5640",
    "province_name": "Namur",
    "province_code": "NA",
    "region": "Wallonie",
    "coordinates": {
      "lat": 50.3167,
      "lng": 4.6667
    },
    "population": 12800
  },
  {
    "name": "Namur",
    "slug": "namur-5000",
    "zip": "5000",
    "province_name": "Namur",
    "province_code": "NA",
    "region": "Wallonie",
    "coordinates": {
      "lat": 50.4674,
      "lng": 4.872
    },
    "population": 112273
  },
  {
    "name": "Ohey",
    "slug": "ohey-5350",
    "zip": "5350",
    "province_name": "Namur",
    "province_code": "NA",
    "region": "Wallonie",
    "coordinates": {
      "lat": 50.4167,
      "lng": 5.1167
    },
    "population": 5000
  },
  {
    "name": "Onhaye",
    "slug": "onhaye-5520",
    "zip": "5520",
    "province_name": "Namur",
    "province_code": "NA",
    "region": "Wallonie",
    "coordinates": {
      "lat": 50.2333,
      "lng": 4.85
    },
    "population": 3200
  },
  {
    "name": "Philippeville",
    "slug": "philippeville-5600",
    "zip": "5600",
    "province_name": "Namur",
    "province_code": "NA",
    "region": "Wallonie",
    "coordinates": {
      "lat": 50.195,
      "lng": 4.5417
    },
    "population": 9255
  },
  {
    "name": "Profondeville",
    "slug": "profondeville-5170",
    "zip": "5170",
    "province_name": "Namur",
    "province_code": "NA",
    "region": "Wallonie",
    "coordinates": {
      "lat": 50.3833,
      "lng": 4.8667
    },
    "population": 12361
  },
  {
    "name": "Rochefort",
    "slug": "rochefort-5580",
    "zip": "5580",
    "province_name": "Namur",
    "province_code": "NA",
    "region": "Wallonie",
    "coordinates": {
      "lat": 50.1603,
      "lng": 5.2222
    },
    "population": 12876
  },
  {
    "name": "Sambreville",
    "slug": "sambreville-5060",
    "zip": "5060",
    "province_name": "Namur",
    "province_code": "NA",
    "region": "Wallonie",
    "coordinates": {
      "lat": 50.4333,
      "lng": 4.6167
    },
    "population": 28311
  },
  {
    "name": "Sombreffe",
    "slug": "sombreffe-5140",
    "zip": "5140",
    "province_name": "Namur",
    "province_code": "NA",
    "region": "Wallonie",
    "coordinates": {
      "lat": 50.5333,
      "lng": 4.6
    },
    "population": 8356
  },
  {
    "name": "Somme-Leuze",
    "slug": "somme-leuze-5377",
    "zip": "5377",
    "province_name": "Namur",
    "province_code": "NA",
    "region": "Wallonie",
    "coordinates": {
      "lat": 50.35,
      "lng": 5.3
    },
    "population": 5600
  },
  {
    "name": "Viroinval",
    "slug": "viroinval-5670",
    "zip": "5670",
    "province_name": "Namur",
    "province_code": "NA",
    "region": "Wallonie",
    "coordinates": {
      "lat": 50.0833,
      "lng": 4.5667
    },
    "population": 5700
  },
  {
    "name": "Vresse-sur-Semois",
    "slug": "vresse-sur-semois-5550",
    "zip": "5550",
    "province_name": "Namur",
    "province_code": "NA",
    "region": "Wallonie",
    "coordinates": {
      "lat": 49.8833,
      "lng": 4.95
    },
    "population": 2700
  },
  {
    "name": "Walcourt",
    "slug": "walcourt-5650",
    "zip": "5650",
    "province_name": "Namur",
    "province_code": "NA",
    "region": "Wallonie",
    "coordinates": {
      "lat": 50.25,
      "lng": 4.4333
    },
    "population": 18500
  },
  {
    "name": "Yvoir",
    "slug": "yvoir-5530",
    "zip": "5530",
    "province_name": "Namur",
    "province_code": "NA",
    "region": "Wallonie",
    "coordinates": {
      "lat": 50.325,
      "lng": 4.8833
    },
    "population": 9189
  },
  {
    "name": "Éghezée",
    "slug": "eghezee-5310",
    "zip": "5310",
    "province_name": "Namur",
    "province_code": "NA",
    "region": "Wallonie",
    "coordinates": {
      "lat": 50.5917,
      "lng": 4.9083
    },
    "population": 16143
  }
]